mudag/__init__.py
mudag/cli/__init__.py
mudag/cli/__main__.py
mudag/cli/cli.py
mudag/core/__init__.py
mudag/core/analyzer.py
mudag/utils/__init__.py
mudag/utils/formatter.py
mudag/utils/git_utils.py
mudag/utils/ignore_patterns.py
mudag/utils/logging_utils.py
mudag-0.1.0.dist-info/LICENSE
mudag-0.1.0.dist-info/METADATA
mudag-0.1.0.dist-info/WHEEL
mudag-0.1.0.dist-info/entry_points.txt
mudag-0.1.0.dist-info/top_level.txt
mudag-0.1.0.dist-info/RECORD
