Metadata-Version: 2.2
Name: mudag
Version: 0.1.0
Summary: A tool for analyzing research software repositories with focus on workflow languages
Home-page: https://github.com/aaronstrachardt/mudag
Author: Aaron Strachardt
Author-email: Aaron Strachardt <your.email@example.com>
License: MIT
Project-URL: Homepage, https://github.com/aaronstrachardt/mudag
Project-URL: Bug Tracker, https://github.com/aaronstrachardt/mudag/issues
Keywords: workflow,research software,code analysis,metrics
Classifier: Development Status :: 3 - Alpha
Classifier: Environment :: Console
Classifier: Intended Audience :: Science/Research
Classifier: License :: OSI Approved :: MIT License
Classifier: Programming Language :: Python :: 3
Classifier: Programming Language :: Python :: 3.7
Classifier: Programming Language :: Python :: 3.8
Classifier: Programming Language :: Python :: 3.9
Classifier: Programming Language :: Python :: 3.10
Classifier: Topic :: Scientific/Engineering
Classifier: Topic :: Software Development :: Quality Assurance
Requires-Python: >=3.7
License-File: LICENSE
Dynamic: author
Dynamic: home-page
Dynamic: requires-python
